nextpyreports/__init__.py
nextpyreports/center.py
nextpyreports/handle_shipment.py
nextpyreports/services/__init__.py
nextpyreports/services/DBService/__init__.py
nextpyreports/services/DBService/center.py
nextpyreports/services/DBService/getThings.py
nextpyreports/services/DBService/lifecycle.py
nextpyreports/services/DBService/models/__init__.py
nextpyreports/services/DBService/models/config_base.py
nextpyreports/services/DBService/models/dynamic_base.py
nextpyreports/services/DBService/models/enums.py
nextpyreports/services/DBService/models/result_base.py
nextpyreports/services/DBService/models/types.py
nextpyreports/services/DBService/sanic_free_shared.py
nextpyreports/services/DBService/shared.py
nextpyreports/services/Endpoints/__init__.py
nextpyreports/services/Endpoints/center.py
nextpyreports/services/Endpoints/errorHandling.py
nextpyreports/services/Endpoints/oneliners.py
nextpyreports/services/SchedularService/__init__.py
nextpyreports/services/SchedularService/center.py
nextpyreports/services/SchedularService/completeTestRun.py
nextpyreports/services/SchedularService/constants.py
nextpyreports/services/SchedularService/handlePending.py
nextpyreports/services/SchedularService/lifecycle.py
nextpyreports/services/SchedularService/modifySuites.py
nextpyreports/services/SchedularService/refer_types.py
nextpyreports/services/SchedularService/shared.py
nextpyreports-0.4.0.dist-info/entry_points.txt
nextpyreports-0.4.0.dist-info/METADATA
nextpyreports-0.4.0.dist-info/WHEEL
nextpyreports-0.4.0.dist-info/RECORD
