Metadata-Version: 2.1
Name: nextpyreports
Version: 0.4.0
Summary: Next Dashboard for test results
License: MIT
Author: Rahul
Author-email: saihanumarahul66@gmail.com
Maintainer: Rahul
Maintainer-email: saihanumarahul66@gmail.com
Requires-Python: >=3.8,<4.0
Classifier: License :: OSI Approved :: MIT License
Classifier: Programming Language :: Python :: 3
Classifier: Programming Language :: Python :: 3.8
Classifier: Programming Language :: Python :: 3.9
Classifier: Programming Language :: Python :: 3.10
Classifier: Programming Language :: Python :: 3.11
Requires-Dist: apscheduler (>=3.10.4,<4.0.0)
Requires-Dist: click (>=8.1.6,<9.0.0)
Requires-Dist: loguru (>=0.7.2,<0.8.0)
Requires-Dist: pydantic (>=2.3.0,<3.0.0)
Requires-Dist: sanic (>=23.6.0,<24.0.0)
Requires-Dist: tortoise-orm (>=0.20.0,<0.21.0)
